friendly_id/__init__.py
friendly_id/friendly_id.py
friendly_id/pydantic_types.py
friendly_id/sqlalchemy_types.py
friendly_id-0.6.1.dist-info/METADATA
friendly_id-0.6.1.dist-info/WHEEL
friendly_id-0.6.1.dist-info/licenses/LICENSE
friendly_id-0.6.1.dist-info/RECORD
