Metadata-Version: 2.4
Name: friendly-id
Version: 0.6.1
Summary: friendly-id is a Python library to generate really unique and url friendly IDs based on UUID and base62
Author-email: Junlin Zhou <jameszhou2108@hotmail.com>
License: Copyright 2022 Junlin Zhou
License-File: LICENSE
Keywords: friendly-id,uuid
Classifier: License :: OSI Approved :: MIT License
Classifier: Programming Language :: Python
Classifier: Programming Language :: Python :: 3
Requires-Python: >=3.9
Provides-Extra: all
Requires-Dist: pydantic>=2.0; extra == 'all'
Requires-Dist: sqlalchemy>=2.0; extra == 'all'
Provides-Extra: pydantic
Requires-Dist: pydantic>=2.0; extra == 'pydantic'
Provides-Extra: sqlalchemy
Requires-Dist: sqlalchemy>=2.0; extra == 'sqlalchemy'
